basebot22/__init__.py
basebot22/_version.py
basebot22/backtest.py
basebot22/basebot.py
basebot22_basebot_JustinGuese-0.3.43.dist-info/METADATA
basebot22_basebot_JustinGuese-0.3.43.dist-info/WHEEL
basebot22_basebot_JustinGuese-0.3.43.dist-info/top_level.txt
basebot22_basebot_JustinGuese-0.3.43.dist-info/RECORD
